audio.py
ff_ad5m_audio-0.4.dist-info/LICENSE
ff_ad5m_audio-0.4.dist-info/METADATA
ff_ad5m_audio-0.4.dist-info/WHEEL
ff_ad5m_audio-0.4.dist-info/entry_points.txt
ff_ad5m_audio-0.4.dist-info/top_level.txt
ff_ad5m_audio-0.4.dist-info/RECORD
