Metadata-Version: 2.1
Name: ff-ad5m-audio
Version: 0.4
Summary: Audio library for FlashForge Adventurer 5M using the pwm device as audio output to play frequencies and midi files.
Author-email: Tristan Timmermans <none@yourbusiness.nowhere>
Maintainer-email: Tristan Timmermans <none@yourbusiness.nowhere>
Keywords: flashforge,adventurer,5m,ad5m,audio,adm5
Requires-Python: >=3.8
License-File: LICENSE
Requires-Dist: mido
